setup.py
ts3LogAnalyzer/__init__.py
ts3LogAnalyzer/schema.sql
ts3LogAnalyzer/ts3LogAnalyzer.py
ts3LogAnalyzer.egg-info/PKG-INFO
ts3LogAnalyzer.egg-info/SOURCES.txt
ts3LogAnalyzer.egg-info/dependency_links.txt
ts3LogAnalyzer.egg-info/entry_points.txt
ts3LogAnalyzer.egg-info/not-zip-safe
ts3LogAnalyzer.egg-info/requires.txt
ts3LogAnalyzer.egg-info/top_level.txt