Metadata-Version: 1.0
Name: ts3LogAnalyzer
Version: 2.1
Summary: A cli utility for analyzing teamspeak 3 server logs.
Home-page: https://github.com/ToFran/TS3LogAnalyzer/
Author: Francisco Marques AKA tofran
Author-email: franscopcmarques@gmail.com
License: GPL V3
Keywords: teamspeak ts3 ts3server ts
Platform: UNKNOWN
